mkdocstrings_handlers/luau/__init__.py
mkdocstrings_handlers/luau/_internal/__init__.py
mkdocstrings_handlers/luau/_internal/config.py
mkdocstrings_handlers/luau/_internal/debug.py
mkdocstrings_handlers/luau/_internal/handler.py
mkdocstrings_handlers/luau/_internal/models.py
mkdocstrings_handlers/luau/_internal/parser.py
mkdocstrings_handlers/luau/py.typed
mkdocstrings_handlers/luau/templates/material/_base/data.html.jinja
mkdocstrings_handlers/luau/templates/material/_base/function.html.jinja
mkdocstrings_handlers/luau/templates/material/_base/module.html.jinja
mkdocstrings_handlers/luau/templates/material/data.html.jinja
mkdocstrings_handlers/luau/templates/material/function.html.jinja
mkdocstrings_handlers/luau/templates/material/module.html.jinja
mkdocstrings_luau-0.1.1.dist-info/METADATA
mkdocstrings_luau-0.1.1.dist-info/WHEEL
mkdocstrings_luau-0.1.1.dist-info/entry_points.txt
mkdocstrings_luau-0.1.1.dist-info/licenses/LICENSE
mkdocstrings_luau-0.1.1.dist-info/RECORD
